aschttp/__init__.py
aschttp/_transport.py
aschttp/awaitables/awaitable.py
aschttp/client.py
aschttp/provider.py
aschttp/types/http_options.py
aschttp/types/interceptors.py
ascender_httpclient-0.1.0.dist-info/LICENSE
ascender_httpclient-0.1.0.dist-info/METADATA
ascender_httpclient-0.1.0.dist-info/WHEEL
ascender_httpclient-0.1.0.dist-info/RECORD
