Metadata-Version: 2.1
Name: ascender-httpclient
Version: 0.1.0
Summary: ascender-httpclient
License: MIT
Author: AscenderTeam
Requires-Python: >=3.11,<4.0
Classifier: License :: OSI Approved :: MIT License
Classifier: Programming Language :: Python :: 3
Classifier: Programming Language :: Python :: 3.11
Classifier: Programming Language :: Python :: 3.12
Requires-Dist: ascender-framework (>=1.3.0b4)
Requires-Dist: httpx (>=0.28.1,<0.29.0)
Requires-Dist: reactivex (>=4.0.4,<5.0.0)
